{
  "projectStructure": {
    "formatVersion": "0.3.3",
    "isPublishedAsRoot": "true",
    "variants": [
      {
        "name": "debugApiElements",
        "sourceSet": [
          "jvmNativeMain",
          "commonMain",
          "javaMain"
        ]
      },
      {
        "name": "debugRuntimeElements",
        "sourceSet": [
          "jvmNativeMain",
          "commonMain",
          "javaMain"
        ]
      },
      {
        "name": "releaseApiElements",
        "sourceSet": [
          "jvmNativeMain",
          "commonMain",
          "javaMain"
        ]
      },
      {
        "name": "releaseRuntimeElements",
        "sourceSet": [
          "jvmNativeMain",
          "commonMain",
          "javaMain"
        ]
      },
      {
        "name": "desktopApiElements",
        "sourceSet": [
          "jvmNativeMain",
          "javaMain",
          "skikoMain",
          "commonMain"
        ]
      },
      {
        "name": "desktopRuntimeElements",
        "sourceSet": [
          "jvmNativeMain",
          "javaMain",
          "skikoMain",
          "commonMain"
        ]
      },
      {
        "name": "iosArm64ApiElements",
        "sourceSet": [
          "iosMain",
          "appleMain",
          "nativeMain",
          "jvmNativeMain",
          "commonMain",
          "skikoMain"
        ]
      },
      {
        "name": "iosSimulatorArm64ApiElements",
        "sourceSet": [
          "iosMain",
          "appleMain",
          "nativeMain",
          "commonMain",
          "jvmNativeMain",
          "skikoMain"
        ]
      },
      {
        "name": "iosX64ApiElements",
        "sourceSet": [
          "iosMain",
          "appleMain",
          "nativeMain",
          "commonMain",
          "jvmNativeMain",
          "skikoMain"
        ]
      },
      {
        "name": "jsApiElements",
        "sourceSet": [
          "webMain",
          "skikoMain",
          "commonMain"
        ]
      },
      {
        "name": "jsRuntimeElements",
        "sourceSet": [
          "webMain",
          "skikoMain",
          "commonMain"
        ]
      },
      {
        "name": "macosArm64ApiElements",
        "sourceSet": [
          "macosMain",
          "appleMain",
          "nativeMain",
          "commonMain",
          "jvmNativeMain",
          "skikoMain"
        ]
      },
      {
        "name": "macosX64ApiElements",
        "sourceSet": [
          "macosMain",
          "appleMain",
          "nativeMain",
          "commonMain",
          "jvmNativeMain",
          "skikoMain"
        ]
      },
      {
        "name": "wasmJsApiElements",
        "sourceSet": [
          "webMain",
          "commonMain",
          "skikoMain"
        ]
      },
      {
        "name": "wasmJsRuntimeElements",
        "sourceSet": [
          "webMain",
          "commonMain",
          "skikoMain"
        ]
      }
    ],
    "sourceSets": [
      {
        "name": "appleMain",
        "dependsOn": [
          "nativeMain"
        ],
        "moduleDependency": [
          "io.github.alexzhirkevich:compottie-core",
          "org.jetbrains.compose.foundation:foundation",
          "io.github.alexzhirkevich:keight"
        ],
        "sourceSetCInteropMetadataDirectory": "appleMain-cinterop",
        "binaryLayout": "klib",
        "hostSpecific": "true"
      },
      {
        "name": "commonMain",
        "dependsOn": [],
        "moduleDependency": [
          "io.github.alexzhirkevich:compottie-core",
          "org.jetbrains.kotlin:kotlin-stdlib",
          "org.jetbrains.compose.foundation:foundation",
          "io.github.alexzhirkevich:keight"
        ],
        "binaryLayout": "klib"
      },
      {
        "name": "iosMain",
        "dependsOn": [
          "appleMain"
        ],
        "moduleDependency": [
          "io.github.alexzhirkevich:compottie-core",
          "org.jetbrains.compose.foundation:foundation",
          "io.github.alexzhirkevich:keight"
        ],
        "sourceSetCInteropMetadataDirectory": "iosMain-cinterop",
        "binaryLayout": "klib",
        "hostSpecific": "true"
      },
      {
        "name": "javaMain",
        "dependsOn": [
          "commonMain"
        ],
        "moduleDependency": [
          "io.github.alexzhirkevich:compottie-core",
          "org.jetbrains.kotlin:kotlin-stdlib",
          "org.jetbrains.compose.foundation:foundation",
          "io.github.alexzhirkevich:keight"
        ],
        "binaryLayout": "klib"
      },
      {
        "name": "jvmNativeMain",
        "dependsOn": [
          "commonMain"
        ],
        "moduleDependency": [
          "io.github.alexzhirkevich:compottie-core",
          "org.jetbrains.kotlin:kotlin-stdlib",
          "org.jetbrains.compose.foundation:foundation",
          "io.github.alexzhirkevich:keight"
        ],
        "binaryLayout": "klib"
      },
      {
        "name": "macosMain",
        "dependsOn": [
          "appleMain"
        ],
        "moduleDependency": [
          "io.github.alexzhirkevich:compottie-core",
          "org.jetbrains.compose.foundation:foundation",
          "io.github.alexzhirkevich:keight"
        ],
        "sourceSetCInteropMetadataDirectory": "macosMain-cinterop",
        "binaryLayout": "klib",
        "hostSpecific": "true"
      },
      {
        "name": "nativeMain",
        "dependsOn": [
          "commonMain"
        ],
        "moduleDependency": [
          "io.github.alexzhirkevich:compottie-core",
          "org.jetbrains.compose.foundation:foundation",
          "io.github.alexzhirkevich:keight"
        ],
        "sourceSetCInteropMetadataDirectory": "nativeMain-cinterop",
        "binaryLayout": "klib",
        "hostSpecific": "true"
      },
      {
        "name": "skikoMain",
        "dependsOn": [
          "commonMain"
        ],
        "moduleDependency": [
          "io.github.alexzhirkevich:compottie-core",
          "org.jetbrains.kotlin:kotlin-stdlib",
          "org.jetbrains.compose.foundation:foundation",
          "io.github.alexzhirkevich:keight"
        ],
        "binaryLayout": "klib"
      },
      {
        "name": "webMain",
        "dependsOn": [
          "commonMain"
        ],
        "moduleDependency": [
          "io.github.alexzhirkevich:compottie-core",
          "org.jetbrains.kotlin:kotlin-stdlib",
          "org.jetbrains.compose.foundation:foundation",
          "io.github.alexzhirkevich:keight"
        ],
        "binaryLayout": "klib"
      }
    ]
  }
}